[
    {
        "Id": 10264,
        "ParentId": 10151,
        "TypeLevel": "2",
        "TypeName": "连裤袜",
        "Path": "0->10151->10264",
        "SortNum": 1,
        "FullName": "内衣袜品->连裤袜",
        "CateID": "",
        "Parameters": null,
        "KeyWord": "连裤袜",
        "Attributes": null,
        "SortType": null,
        "FilterQuery": "",
        "IconName": "",
        "Logo": "http://i8.m.vancl.com/oms/2015_8_24_14_36_41_8264.jpg",
        "Version": 1
    },
    {
        "Id": 10372,
        "ParentId": 10151,
        "TypeLevel": "2",
        "TypeName": "打底裤",
        "Path": "0->10151->10372",
        "SortNum": 2,
        "FullName": "袜品->打底裤",
        "CateID": "",
        "Parameters": null,
        "KeyWord": "打底裤",
        "Attributes": null,
        "SortType": null,
        "FilterQuery": "",
        "IconName": "",
        "Logo": "http://i4.m.vancl.com/oms/2015_10_12_17_6_14_4263.jpg",
        "Version": 1
    },
    {
        "Id": 10265,
        "ParentId": 10151,
        "TypeLevel": "2",
        "TypeName": "棉袜",
        "Path": "0->10151->10265",
        "SortNum": 3,
        "FullName": "内衣袜品->棉袜",
        "CateID": "27886",
        "Parameters": null,
        "KeyWord": "",
        "Attributes": null,
        "SortType": null,
        "FilterQuery": "",
        "IconName": "",
        "Logo": "http://i6.m.vancl.com/oms/2015_8_24_14_43_42_6578.jpg",
        "Version": 1
    }
]